setup.py
mnp_distributions/Binomialdistribution.py
mnp_distributions/Gaussiandistribution.py
mnp_distributions/Generaldistribution.py
mnp_distributions/__init__.py
mnp_distributions.egg-info/PKG-INFO
mnp_distributions.egg-info/SOURCES.txt
mnp_distributions.egg-info/dependency_links.txt
mnp_distributions.egg-info/not-zip-safe
mnp_distributions.egg-info/top_level.txt